{
  "location": [
    {
      "id": 1,
      "tenkhuvuc": "Miền trung1",
      "mota": "Miền trung",
      "tinhthanh": "Đà nẵng"
    },
    {
      "id": 2,
      "tenkhuvuc": "Miền trung",
      "mota": "Miền trung",
      "tinhthanh": "Huế"
    },
    {
      "id": 3,
      "tenkhuvuc": "Miền trung",
      "mota": "Miền trung",
      "tinhthanh": "Quảng Bình"
    },
    {
      "id": 4,
      "tenkhuvuc": "Miền trung",
      "mota": "Miền trung",
      "tinhthanh": "Quảng Trị"
    },
    {
      "id": 5,
      "tenkhuvuc": "Miền trung",
      "mota": "Miền trung",
      "tinhthanh": "Bình Định"
    },
    {
      "id": 12,
      "tenkhuvuc": "Miền trung",
      "mota": "Miền trung",
      "tinhthanh": "Bình Thuận"
    }
  ]
}